Metadata-Version: 1.0
Name: suds3
Version: 0.1
Summary: Lightweight SOAP client
Home-page: https://bitbucket.org/eternalconcert/suds3
Author: Christian Kokoska 
Author-email: christian.kokoska@gmx.de
License: UNKNOWN
Platform: UNKNOWN
